jrmpc/__init__.py
jrmpc/numpy.py
jrmpc/torch.py
jrmpc-1.0.0.dist-info/METADATA
jrmpc-1.0.0.dist-info/WHEEL
jrmpc-1.0.0.dist-info/top_level.txt
jrmpc-1.0.0.dist-info/RECORD
