Metadata-Version: 2.1
Name: jrmpc
Version: 1.0.0
Summary: Numpy & PyTorch implementation of the JRMPC algorithm.
Author: PCR Research
Project-URL: Repository, https://github.com/pcrresearch/JRMPC-PyTorch-Numpy.git
Classifier: Programming Language :: Python :: 3
Classifier: License :: OSI Approved :: MIT License
Classifier: Operating System :: OS Independent
Requires-Python: >=3.7
Requires-Dist: numpy
Requires-Dist: tqdm
Requires-Dist: typing-extensions ; python_version < "3.10"
